[
  {
    "timestamp": "2024-01-02T14:30:00Z",
    "open": 320.0,
    "high": 320.2545,
    "low": 319.8182,
    "close": 319.6365,
    "volume": 1013329
  },
  {
    "timestamp": "2024-01-02T14:31:00Z",
    "open": 319.6365,
    "high": 319.7678,
    "low": 319.5427,
    "close": 319.8241,
    "volume": 831837
  },
  {
    "timestamp": "2024-01-02T14:32:00Z",
    "open": 319.8241,
    "high": 320.0241,
    "low": 319.6812,
    "close": 319.5384,
    "volume": 1079668
  },
  {
    "timestamp": "2024-01-02T14:33:00Z",
    "open": 319.5384,
    "high": 319.7715,
    "low": 319.3718,
    "close": 319.8715,
    "volume": 1261342
  },
  {
    "timestamp": "2024-01-02T14:34:00Z",
    "open": 319.8715,
    "high": 319.989,
    "low": 319.7875,
    "close": 320.0394,
    "volume": 817014
  },
  {
    "timestamp": "2024-01-02T14:35:00Z",
    "open": 320.0394,
    "high": 320.0737,
    "low": 320.0148,
    "close": 319.9902,
    "volume": 1260790
  },
  {
    "timestamp": "2024-01-02T14:36:00Z",
    "open": 319.9902,
    "high": 320.0127,
    "low": 319.9742,
    "close": 319.9581,
    "volume": 1002224
  },
  {
    "timestamp": "2024-01-02T14:37:00Z",
    "open": 319.9581,
    "high": 320.0411,
    "low": 319.8988,
    "close": 320.0767,
    "volume": 926946
  },
  {
    "timestamp": "2024-01-02T14:38:00Z",
    "open": 320.0767,
    "high": 320.1887,
    "low": 319.9967,
    "close": 319.9168,
    "volume": 1206108
  },
  {
    "timestamp": "2024-01-02T14:39:00Z",
    "open": 319.9168,
    "high": 320.0002,
    "low": 319.8571,
    "close": 319.7975,
    "volume": 905845
  },
  {
    "timestamp": "2024-01-02T14:40:00Z",
    "open": 319.7975,
    "high": 319.818,
    "low": 319.7829,
    "close": 319.7683,
    "volume": 1041008
  },
  {
    "timestamp": "2024-01-02T14:41:00Z",
    "open": 319.7683,
    "high": 319.8722,
    "low": 319.694,
    "close": 319.9168,
    "volume": 1310664
  },
  {
    "timestamp": "2024-01-02T14:42:00Z",
    "open": 319.9168,
    "high": 320.0319,
    "low": 319.8345,
    "close": 319.7523,
    "volume": 927652
  },
  {
    "timestamp": "2024-01-02T14:43:00Z",
    "open": 319.7523,
    "high": 319.8843,
    "low": 319.658,
    "close": 319.9409,
    "volume": 936454
  },
  {
    "timestamp": "2024-01-02T14:44:00Z",
    "open": 319.9409,
    "high": 319.9509,
    "low": 319.9337,
    "close": 319.9265,
    "volume": 968347
  },
  {
    "timestamp": "2024-01-02T14:45:00Z",
    "open": 319.9265,
    "high": 320.1286,
    "low": 319.7821,
    "close": 320.2153,
    "volume": 1201766
  },
  {
    "timestamp": "2024-01-02T14:46:00Z",
    "open": 320.2153,
    "high": 320.2222,
    "low": 320.2103,
    "close": 320.2053,
    "volume": 916604
  },
  {
    "timestamp": "2024-01-02T14:47:00Z",
    "open": 320.2053,
    "high": 320.2429,
    "low": 320.1785,
    "close": 320.259,
    "volume": 1373727
  },
  {
    "timestamp": "2024-01-02T14:48:00Z",
    "open": 320.259,
    "high": 320.356,
    "low": 320.1896,
    "close": 320.3976,
    "volume": 1141580
  },
  {
    "timestamp": "2024-01-02T14:49:00Z",
    "open": 320.3976,
    "high": 320.562,
    "low": 320.2801,
    "close": 320.6325,
    "volume": 952744
  },
  {
    "timestamp": "2024-01-02T14:50:00Z",
    "open": 320.6325,
    "high": 320.8661,
    "low": 320.4657,
    "close": 320.9662,
    "volume": 1049029
  },
  {
    "timestamp": "2024-01-02T14:51:00Z",
    "open": 320.9662,
    "high": 321.0374,
    "low": 320.9153,
    "close": 321.068,
    "volume": 848084
  },
  {
    "timestamp": "2024-01-02T14:52:00Z",
    "open": 321.068,
    "high": 321.1128,
    "low": 321.0359,
    "close": 321.132,
    "volume": 1173937
  },
  {
    "timestamp": "2024-01-02T14:53:00Z",
    "open": 321.132,
    "high": 321.2909,
    "low": 321.0185,
    "close": 321.359,
    "volume": 1292654
  },
  {
    "timestamp": "2024-01-02T14:54:00Z",
    "open": 321.359,
    "high": 321.3779,
    "low": 321.3455,
    "close": 321.332,
    "volume": 1103846
  },
  {
    "timestamp": "2024-01-02T14:55:00Z",
    "open": 321.332,
    "high": 321.4542,
    "low": 321.2447,
    "close": 321.1575,
    "volume": 1026477
  },
  {
    "timestamp": "2024-01-02T14:56:00Z",
    "open": 321.1575,
    "high": 321.3783,
    "low": 320.9997,
    "close": 320.842,
    "volume": 1132508
  },
  {
    "timestamp": "2024-01-02T14:57:00Z",
    "open": 320.842,
    "high": 321.0642,
    "low": 320.6833,
    "close": 321.1594,
    "volume": 1382033
  },
  {
    "timestamp": "2024-01-02T14:58:00Z",
    "open": 321.1594,
    "high": 321.3281,
    "low": 321.0389,
    "close": 321.4003,
    "volume": 869377
  },
  {
    "timestamp": "2024-01-02T14:59:00Z",
    "open": 321.4003,
    "high": 321.5827,
    "low": 321.2701,
    "close": 321.6608,
    "volume": 1069840
  },
  {
    "timestamp": "2024-01-02T15:00:00Z",
    "open": 321.6608,
    "high": 321.781,
    "low": 321.575,
    "close": 321.8325,
    "volume": 1161806
  },
  {
    "timestamp": "2024-01-02T15:01:00Z",
    "open": 321.8325,
    "high": 322.0858,
    "low": 321.6515,
    "close": 322.1944,
    "volume": 802025
  },
  {
    "timestamp": "2024-01-02T15:02:00Z",
    "open": 322.1944,
    "high": 322.3958,
    "low": 322.0505,
    "close": 321.9067,
    "volume": 1013727
  },
  {
    "timestamp": "2024-01-02T15:03:00Z",
    "open": 321.9067,
    "high": 322.0143,
    "low": 321.8298,
    "close": 321.7529,
    "volume": 873039
  },
  {
    "timestamp": "2024-01-02T15:04:00Z",
    "open": 321.7529,
    "high": 322.0219,
    "low": 321.5608,
    "close": 321.3686,
    "volume": 1269677
  },
  {
    "timestamp": "2024-01-02T15:05:00Z",
    "open": 321.3686,
    "high": 321.4696,
    "low": 321.2965,
    "close": 321.2243,
    "volume": 1124654
  },
  {
    "timestamp": "2024-01-02T15:06:00Z",
    "open": 321.2243,
    "high": 321.3108,
    "low": 321.1625,
    "close": 321.1007,
    "volume": 814319
  },
  {
    "timestamp": "2024-01-02T15:07:00Z",
    "open": 321.1007,
    "high": 321.2459,
    "low": 320.997,
    "close": 321.3081,
    "volume": 1180925
  },
  {
    "timestamp": "2024-01-02T15:08:00Z",
    "open": 321.3081,
    "high": 321.4339,
    "low": 321.2183,
    "close": 321.1285,
    "volume": 1055610
  },
  {
    "timestamp": "2024-01-02T15:09:00Z",
    "open": 321.1285,
    "high": 321.3912,
    "low": 320.9409,
    "close": 320.7533,
    "volume": 1372299
  },
  {
    "timestamp": "2024-01-02T15:10:00Z",
    "open": 320.7533,
    "high": 320.9702,
    "low": 320.5984,
    "close": 321.0631,
    "volume": 1249801
  },
  {
    "timestamp": "2024-01-02T15:11:00Z",
    "open": 321.0631,
    "high": 321.2244,
    "low": 320.9479,
    "close": 320.8327,
    "volume": 1302206
  },
  {
    "timestamp": "2024-01-02T15:12:00Z",
    "open": 320.8327,
    "high": 320.9865,
    "low": 320.7228,
    "close": 320.6129,
    "volume": 848638
  },
  {
    "timestamp": "2024-01-02T15:13:00Z",
    "open": 320.6129,
    "high": 320.7812,
    "low": 320.4928,
    "close": 320.3726,
    "volume": 1270532
  },
  {
    "timestamp": "2024-01-02T15:14:00Z",
    "open": 320.3726,
    "high": 320.5777,
    "low": 320.226,
    "close": 320.6657,
    "volume": 1105712
  },
  {
    "timestamp": "2024-01-02T15:15:00Z",
    "open": 320.6657,
    "high": 320.7948,
    "low": 320.5734,
    "close": 320.8502,
    "volume": 841634
  },
  {
    "timestamp": "2024-01-02T15:16:00Z",
    "open": 320.8502,
    "high": 321.1162,
    "low": 320.6602,
    "close": 320.4702,
    "volume": 1115086
  },
  {
    "timestamp": "2024-01-02T15:17:00Z",
    "open": 320.4702,
    "high": 320.5389,
    "low": 320.4211,
    "close": 320.5684,
    "volume": 851993
  },
  {
    "timestamp": "2024-01-02T15:18:00Z",
    "open": 320.5684,
    "high": 320.706,
    "low": 320.4702,
    "close": 320.3719,
    "volume": 943809
  },
  {
    "timestamp": "2024-01-02T15:19:00Z",
    "open": 320.3719,
    "high": 320.4017,
    "low": 320.3507,
    "close": 320.3294,
    "volume": 1276563
  },
  {
    "timestamp": "2024-01-02T15:20:00Z",
    "open": 320.3294,
    "high": 320.5048,
    "low": 320.2041,
    "close": 320.0789,
    "volume": 1235146
  },
  {
    "timestamp": "2024-01-02T15:21:00Z",
    "open": 320.0789,
    "high": 320.2102,
    "low": 319.9851,
    "close": 319.8913,
    "volume": 1281941
  },
  {
    "timestamp": "2024-01-02T15:22:00Z",
    "open": 319.8913,
    "high": 319.932,
    "low": 319.8623,
    "close": 319.9494,
    "volume": 1343902
  },
  {
    "timestamp": "2024-01-02T15:23:00Z",
    "open": 319.9494,
    "high": 320.1111,
    "low": 319.8339,
    "close": 319.7184,
    "volume": 822486
  },
  {
    "timestamp": "2024-01-02T15:24:00Z",
    "open": 319.7184,
    "high": 319.9435,
    "low": 319.5575,
    "close": 319.3967,
    "volume": 1263664
  },
  {
    "timestamp": "2024-01-02T15:25:00Z",
    "open": 319.3967,
    "high": 319.6473,
    "low": 319.2177,
    "close": 319.0386,
    "volume": 912008
  },
  {
    "timestamp": "2024-01-02T15:26:00Z",
    "open": 319.0386,
    "high": 319.1743,
    "low": 318.9417,
    "close": 319.2325,
    "volume": 889809
  },
  {
    "timestamp": "2024-01-02T15:27:00Z",
    "open": 319.2325,
    "high": 319.405,
    "low": 319.1092,
    "close": 318.986,
    "volume": 906409
  },
  {
    "timestamp": "2024-01-02T15:28:00Z",
    "open": 318.986,
    "high": 319.0372,
    "low": 318.9494,
    "close": 318.9128,
    "volume": 1320183
  },
  {
    "timestamp": "2024-01-02T15:29:00Z",
    "open": 318.9128,
    "high": 319.1708,
    "low": 318.7285,
    "close": 318.5442,
    "volume": 915568
  }
]